synspace/__init__.py
synspace/data.py
synspace/draw.py
synspace/synspace.py
synspace/utils.py
synspace/version.py
synspace/reos/__init__.py
synspace/reos/data/alert_collection.csv
synspace/rxn_data/blocks.pk.bz2
synspace/rxn_data/rxns.json
synspace-1.0.0.dist-info/licenses/LICENSE
synspace-1.0.0.dist-info/licenses/NOTICE.txt
synspace-1.0.0.dist-info/METADATA
synspace-1.0.0.dist-info/WHEEL
synspace-1.0.0.dist-info/top_level.txt
synspace-1.0.0.dist-info/RECORD
