Metadata-Version: 2.4
Name: synspace
Version: 1.0.0
Summary: Generative model based on forward synthesis rules
Home-page: https://github.com/whitead/synspace
Author: Andrew White
Author-email: andrew.white@rochester.edu
License: MIT
Classifier: Programming Language :: Python :: 3
Classifier: License :: OSI Approved :: MIT License
Classifier: Operating System :: OS Independent
License-File: LICENSE
License-File: NOTICE.txt
Requires-Dist: rdkit
Requires-Dist: tqdm
Requires-Dist: numpy
Requires-Dist: importlib_resources
Requires-Dist: requests
Requires-Dist: pandas
Requires-Dist: skunk
Dynamic: author
Dynamic: author-email
Dynamic: classifier
Dynamic: description
Dynamic: description-content-type
Dynamic: home-page
Dynamic: license
Dynamic: license-file
Dynamic: requires-dist
Dynamic: summary
